MANIFEST.in
README.rst
setup.py
docs/HISTORY.txt
docs/LICENSE.GPL
docs/LICENSE.txt
docs/screenshot.png
ftw/__init__.py
ftw.datepicker.egg-info/PKG-INFO
ftw.datepicker.egg-info/SOURCES.txt
ftw.datepicker.egg-info/dependency_links.txt
ftw.datepicker.egg-info/entry_points.txt
ftw.datepicker.egg-info/namespace_packages.txt
ftw.datepicker.egg-info/not-zip-safe
ftw.datepicker.egg-info/requires.txt
ftw.datepicker.egg-info/top_level.txt
ftw/datepicker/__init__.py
ftw/datepicker/configure.zcml
ftw/datepicker/converter.py
ftw/datepicker/interfaces.py
ftw/datepicker/testing.py
ftw/datepicker/widget.py
ftw/datepicker/locales/ftw.datepicker.pot
ftw/datepicker/locales/de/LC_MESSAGES/ftw.datepicker.po
ftw/datepicker/locales/fr/LC_MESSAGES/ftw.datepicker.po
ftw/datepicker/profiles/default/browserlayer.xml
ftw/datepicker/profiles/default/cssregistry.xml
ftw/datepicker/profiles/default/jsregistry.xml
ftw/datepicker/profiles/default/metadata.xml
ftw/datepicker/profiles/default/registry.xml
ftw/datepicker/profiles/default_plone5/browserlayer.xml
ftw/datepicker/profiles/default_plone5/metadata.xml
ftw/datepicker/profiles/default_plone5/registry.xml
ftw/datepicker/profiles/uninstall_plone5/registry.xml
ftw/datepicker/resources/datepicker-compiled.css
ftw/datepicker/resources/main.css
ftw/datepicker/resources/js/datepicker-compiled.js
ftw/datepicker/resources/js/datetimepicker_widget.js
ftw/datepicker/resources/js/jquery-mousewheel.js
ftw/datepicker/resources/js/main.js
ftw/datepicker/resources/js/datetimepicker-2.5.18/MIT-LICENSE.txt
ftw/datepicker/resources/js/datetimepicker-2.5.18/jquery.datetimepicker.css
ftw/datepicker/resources/js/datetimepicker-2.5.18/jquery.datetimepicker.full.js
ftw/datepicker/resources/js/datetimepicker-2.5.18/jquery.datetimepicker.js
ftw/datepicker/templates/datetimepicker_input.pt
ftw/datepicker/tests/__init__.py
ftw/datepicker/tests/test_config.py
ftw/datepicker/tests/test_dateconverter.py
ftw/datepicker/tests/test_datetimeconverter.py
ftw/datepicker/tests/test_widget.py
ftw/datepicker/tests/test_widget_second_language.py
ftw/datepicker/tests/views/__init__.py
ftw/datepicker/tests/views/configure.zcml
ftw/datepicker/tests/views/z3cforms.py
ftw/datepicker/upgrades/__init__.py
ftw/datepicker/upgrades/configure.zcml
