Metadata-Version: 2.1
Name: ftw.datepicker
Version: 1.6.2
Summary: A z3c.form datepicker widget (Maintainer Thomas Buchberger)
Home-page: https://github.com/4teamwork/ftw.datepicker
Author: Thomas Buchberger, 4teamwork AG
Author-email: mailto:info@4teamwork.ch
Maintainer: Thomas Buchberger
License: GPL2
Keywords: ftw 4teamwork widget date picker
Platform: UNKNOWN
Classifier: Framework :: Plone
Classifier: Framework :: Plone :: 4.3
Classifier: Framework :: Plone :: 5.1
Classifier: Intended Audience :: Developers
Classifier: Programming Language :: Python
Provides-Extra: tests
